QQbot_Python/__init__.py
QQbot_Python/api.py
QQbot_Python/audio.py
QQbot_Python/channel.py
QQbot_Python/client.py
QQbot_Python/config.py
QQbot_Python/connection.py
QQbot_Python/errors.py
QQbot_Python/flags.py
QQbot_Python/forum.py
QQbot_Python/gateway.py
QQbot_Python/guild.py
QQbot_Python/http.py
QQbot_Python/interaction.py
QQbot_Python/logging.py
QQbot_Python/manage.py
QQbot_Python/message.py
QQbot_Python/reaction.py
QQbot_Python/robot.py
QQbot_Python/user.py
QQbot_Python/ext/__init__.py
QQbot_Python/ext/command_util.py
QQbot_Python/ext/channel_jump/__init__.py
QQbot_Python/ext/cog_apscheduler/__init__.py
QQbot_Python/ext/cog_yaml/__init__.py
QQbot_Python/ext/convert_color/__init__.py
QQbot_Python/types/__init__.py
QQbot_Python/types/announce.py
QQbot_Python/types/audio.py
QQbot_Python/types/channel.py
QQbot_Python/types/emoji.py
QQbot_Python/types/forum.py
QQbot_Python/types/gateway.py
QQbot_Python/types/guild.py
QQbot_Python/types/inline.py
QQbot_Python/types/interaction.py
QQbot_Python/types/message.py
QQbot_Python/types/permission.py
QQbot_Python/types/pins_message.py
QQbot_Python/types/reaction.py
QQbot_Python/types/rich_text.py
QQbot_Python/types/robot.py
QQbot_Python/types/schedule.py
QQbot_Python/types/session.py
QQbot_Python/types/user.py
QQbot_Python-1.1.dist-info/LICENSE
QQbot_Python-1.1.dist-info/METADATA
QQbot_Python-1.1.dist-info/WHEEL
QQbot_Python-1.1.dist-info/top_level.txt
QQbot_Python-1.1.dist-info/RECORD
