Metadata-Version: 2.1
Name: QQbot_Python
Version: 1.1
Summary: 一个非常NB的包
Author: buchilizi
Author-email: 2793415370@qq.com
Classifier: Programming Language :: Python :: 3
Classifier: License :: OSI Approved :: MIT License
Classifier: Operating System :: OS Independent
Requires-Python: >=3
License-File: LICENSE
Requires-Dist: websocket-client
Requires-Dist: qq-botpy
